Workbook

Sheet Условие
A1: Лабораторная работа №2. Задачи линейного программирования. Вариант 8
A3: Магазин оптовой торговли продаёт товары П1, П2, П3. Ограничены полезная площадь (450 м²) и рабочее время (600 чел.-ч). Товарооборот должен быть не меньше 240 тыс. р. Нужно найти план товарооборота с максимальной прибылью.
A5: Показатель | B5: П1 | C5: П2 | D5: П3 | E5: Знак | F5: Объём ресурса | G5: Пояснение
A6: Полезная площадь, м² | B6: 1.5 | C6: 2 | D6: 3 | E6: ≤ | F6: 450 | G6: затраты площади на 1 тыс. р. товарооборота
A7: Рабочее время, чел.-ч | B7: 3 | C7: 2 | D7: 1.5 | E7: ≤ | F7: 600 | G7: затраты времени на 1 тыс. р. товарооборота
A8: Товарооборот, тыс. р. | B8: 1 | C8: 1 | D8: 1 | E8: ≥ | F8: 240 | G8: каждая единица плана - это 1 тыс. р. товарооборота
A9: Прибыль, ден. ед. | B9: 50 | C9: 65 | D9: 70 | E9: → max | G9: прибыль с 1 тыс. р. товарооборота
A10: Допущение: в задаче затраты и прибыль заданы на 1 тыс. р. товарооборота (так в первоисточнике задачи), поэтому переменная xj - это товарооборот товара Пj в тыс. р., а весь товарооборот = x1 + x2 + x3.
A13: 1. Математическая модель прямой задачи
A14: Переменные | B14: x1, x2, x3 - сколько тыс. р. товарооборота запланировать по товарам П1, П2, П3.
A15: Целевая функция | B15: Z = 50·x1 + 65·x2 + 70·x3 → max (суммарная прибыль)
A16: Ограничение 1 | B16: 1,5·x1 + 2·x2 + 3·x3 ≤ 450 (площади нужно не больше, чем есть)
A17: Ограничение 2 | B17: 3·x1 + 2·x2 + 1,5·x3 ≤ 600 (рабочего времени нужно не больше, чем есть)
A18: Ограничение 3 | B18: x1 + x2 + x3 ≥ 240 (товарооборот не меньше 240 тыс. р.)
A19: Неотрицательность | B19: x1 ≥ 0, x2 ≥ 0, x3 ≥ 0 (продать «минус» товар нельзя)
A21: 2. Математическая модель двойственной задачи
A22: Для задачи на max все ограничения приводят к виду «≤». Третье умножаем на −1: −x1 − x2 − x3 ≤ −240. Каждому ограничению прямой задачи соответствует своя двойственная переменная (оценка ресурса).
A23: Переменные | B23: y1 - оценка 1 м² площади, y2 - оценка 1 чел.-ч, y3 - оценка требования по товарообороту (ден. ед.).
A24: Целевая функция | B24: f = 450·y1 + 600·y2 − 240·y3 → min (суммарная оценка всех ресурсов)
A25: Ограничение П1 | B25: 1,5·y1 + 3·y2 − y3 ≥ 50
A26: Ограничение П2 | B26: 2·y1 + 2·y2 − y3 ≥ 65
A27: Ограничение П3 | B27: 3·y1 + 1,5·y2 − y3 ≥ 70
A28: Смысл ограничений | B28: ресурсы, потраченные на 1 тыс. р. товара, «стоят» не меньше прибыли от него
A29: Неотрицательность | B29: y1 ≥ 0, y2 ≥ 0, y3 ≥ 0

Sheet Отчет о результатах 1
A1: Microsoft Excel 16.0 Отчет о результатах
A2: Лист: [ЛР2 В8 Деверилин 451003.xlsx]Прямая задача
A3: Отчет создан: 11/10/2026 16:56:18
A4: Результат: Решение найдено. Все ограничения и условия оптимальности выполнены.
A5: Модуль поиска решения
B6: Модуль: Поиск решения лин. задач симплекс-методом
B7: Время решения: 0.015 секунд.
B8: Число итераций: 4 Число подзадач: 0
A9: Параметры поиска решения
B10: Максимальное время Без пределов, Число итераций Без пределов, Precision 0.000001, Использовать автоматическое масштабирование
B11: Максимальное число подзадач Без пределов, Максимальное число целочисленных решений Без пределов, Целочисленное отклонение 1%, Считать неотрицательными
A14: Ячейка целевой функции (Максимум)
B15: Ячейка | C15: Имя | D15: Исходное значение | E15: Окончательное значение
B16: $F$6 | C16: Z = | D16: 14750 | E16: 14750
A19: Ячейки переменных
B20: Ячейка | C20: Имя | D20: Исходное значение | E20: Окончательное значение | F20: Целочисленное
B21: $B$5 | C21: План, тыс. р. товарооборота x1 (П1) | D21: 100 | E21: 100 | F21: Продолжить
B22: $C$5 | C22: План, тыс. р. товарооборота x2 (П2) | D22: 150 | E22: 150 | F22: Продолжить
B23: $D$5 | C23: План, тыс. р. товарооборота x3 (П3) | D23: 0 | E23: 0 | F23: Продолжить
A26: Ограничения
B27: Ячейка | C27: Имя | D27: Значение ячейки | E27: Формула | F27: Состояние | G27: Допуск
B28: $E$9 | C28: Площадь, м² Левая часть | D28: 450 | E28: $E$9<=$G$9 | F28: Привязка | G28: 0
B29: $E$10 | C29: Рабочее время, чел.-ч Левая часть | D29: 600 | E29: $E$10<=$G$10 | F29: Привязка | G29: 0
B30: $E$11 | C30: Товарооборот, тыс. р. Левая часть | D30: 250 | E30: $E$11>=$G$11 | F30: Без привязки | G30: 10

Sheet Отчет об устойчивости 1
A1: Microsoft Excel 16.0 Отчет об устойчивости
A2: Лист: [ЛР2 В8 Деверилин 451003.xlsx]Прямая задача
A3: Отчет создан: 11/10/2026 16:56:18
A6: Ячейки переменных
D7: Окончательное | E7: Приведенн. | F7: Целевая функция | G7: Допустимое | H7: Допустимое
B8: Ячейка | C8: Имя | D8: Значение | E8: Стоимость | F8: Коэффициент | G8: Увеличение | H8: Уменьшение
B9: $B$5 | C9: План, тыс. р. товарооборота x1 (П1) | D9: 100 | E9: 0 | F9: 50 | G9: 26.25 | H9: 1.25
B10: $C$5 | C10: План, тыс. р. товарооборота x2 (П2) | D10: 150 | E10: 0 | F10: 65 | G10: 1.6666667 | H10: 11.666667
B11: $D$5 | C11: План, тыс. р. товарооборота x3 (П3) | D11: 0 | E11: -26.25 | F11: 70 | G11: 26.25 | H11: 1e+30
A13: Ограничения
D14: Окончательное | E14: Тень | F14: Ограничение | G14: Допустимое | H14: Допустимое
B15: Ячейка | C15: Имя | D15: Значение | E15: Цена | F15: Правая сторона | G15: Увеличение | H15: Уменьшение
B16: $E$9 | C16: Площадь, м² Левая часть | D16: 450 | E16: 31.666667 | F16: 450 | G16: 150 | H16: 30
B17: $E$10 | C17: Рабочее время, чел.-ч Левая часть | D17: 600 | E17: 0.83333333 | F17: 600 | G17: 300 | H17: 60
B18: $E$11 | C18: Товарооборот, тыс. р. Левая часть | D18: 250 | E18: 0 | F18: 240 | G18: 10 | H18: 1e+30

Sheet Отчет о пределах 1
A1: Microsoft Excel 16.0 Отчет о пределах
A2: Лист: [ЛР2 В8 Деверилин 451003.xlsx]Прямая задача
A3: Отчет создан: 11/10/2026 16:56:18
C6: Целевая функция
B7: Ячейка | C7: Имя | D7: Значение
B8: $F$6 | C8: Z = | D8: 14750
C11: Переменная | F11: Нижний | G11: Целевая функция | I11: Верхний | J11: Целевая функция
B12: Ячейка | C12: Имя | D12: Значение | F12: Предел | G12: Результат | I12: Предел | J12: Результат
B13: $B$5 | C13: План, тыс. р. товарооборота x1 (П1) | D13: 100 | F13: 90 | G13: 14250 | I13: 100 | J13: 14750
B14: $C$5 | C14: План, тыс. р. товарооборота x2 (П2) | D14: 150 | F14: 140 | G14: 14100 | I14: 150 | J14: 14750
B15: $D$5 | C15: План, тыс. р. товарооборота x3 (П3) | D15: 0 | F15: 0 | G15: 14750 | I15: 0 | J15: 14750

Sheet Прямая задача
A1: Прямая задача: решение с помощью «Поиск решения»
A4: Переменная | B4: x1 (П1) | C4: x2 (П2) | D4: x3 (П3)
A5: План, тыс. р. товарооборота | B5: 100 | C5: 150 | D5: 0
A6: Прибыль с 1 тыс. р. | B6: =Условие!B9 -> 50 | C6: =Условие!C9 -> 65 | D6: =Условие!D9 -> 70 | E6: Z = | F6: =SUMPRODUCT($B$5:$D$5,B6:D6) -> 14750 | H6: → max
A8: Ограничение | B8: x1 | C8: x2 | D8: x3 | E8: Левая часть | F8: Знак | G8: Правая часть | H8: Остаток | I8: Вывод
A9: Площадь, м² | B9: =Условие!B6 -> 1.5 | C9: =Условие!C6 -> 2 | D9: =Условие!D6 -> 3 | E9: =SUMPRODUCT($B$5:$D$5,B9:D9) -> 450 | F9: <= | G9: =Условие!F6 -> 450 | H9: =G9-E9 -> 0 | I9: =IF(ABS(H9)<0.000001,"израсходован полностью - дефицитный","есть остаток - избыточный") -> израсходован полностью - дефицитный
A10: Рабочее время, чел.-ч | B10: =Условие!B7 -> 3 | C10: =Условие!C7 -> 2 | D10: =Условие!D7 -> 1.5 | E10: =SUMPRODUCT($B$5:$D$5,B10:D10) -> 600 | F10: <= | G10: =Условие!F7 -> 600 | H10: =G10-E10 -> 0 | I10: =IF(ABS(H10)<0.000001,"израсходован полностью - дефицитный","есть остаток - избыточный") -> израсходован полностью - дефицитный
A11: Товарооборот, тыс. р. | B11: =Условие!B8 -> 1 | C11: =Условие!C8 -> 1 | D11: =Условие!D8 -> 1 | E11: =SUMPRODUCT($B$5:$D$5,B11:D11) -> 250 | F11: >= | G11: =Условие!F8 -> 240 | H11: =E11-G11 -> 10 | I11: =IF(H11>=0,"выполнено, запас "&ROUND(H11,2)&" тыс. р.","НЕ выполнено") -> выполнено, запас 10 тыс. р.
A13: Итог | B13: ="Продавать П1 на "&ROUND(B5,2)&" тыс. р., П2 на "&ROUND(C5,2)&" тыс. р., П3 на "&ROUND(D5,2)&" тыс. р. Максимальная прибыль Z = "&ROUND(F6,2)&" ден. ед." -> Продавать П1 на 100 тыс. р., П2 на 150 тыс. р., П3 на 0 тыс. р. Максимальная прибыль Z = 14750 ден. ед.

Sheet Симплекс-метод
A1: Симплекс-метод (ручной расчёт, все числа - формулы)
A5: Итер. | B5: Базис | C5: Cб | D5: b | E5: x1 | F5: x2 | G5: x3 | H5: x4 | I5: x5 | J5: b / a
D6: cj → | E6: =Условие!B9 -> 50 | F6: =Условие!C9 -> 65 | G6: =Условие!D9 -> 70 | H6: 0 | I6: 0
A7: 0 | B7: x4 | C7: =H$6 -> 0 | D7: =Условие!F6 -> 450 | E7: =Условие!B6 -> 1.5 | F7: =Условие!C6 -> 2 | G7: =Условие!D6 -> 3 | H7: 1 | I7: 0 | J7: =IF(G7>0,D7/G7,"-") -> 150
B8: x5 | C8: =I$6 -> 0 | D8: =Условие!F7 -> 600 | E8: =Условие!B7 -> 3 | F8: =Условие!C7 -> 2 | G8: =Условие!D7 -> 1.5 | H8: 0 | I8: 1 | J8: =IF(G8>0,D8/G8,"-") -> 400
B9: Δ | D9: =SUMPRODUCT($C7:$C8,D7:D8) -> 0 | E9: =SUMPRODUCT($C7:$C8,E7:E8)-E6 -> -50 | F9: =SUMPRODUCT($C7:$C8,F7:F8)-F6 -> -65 | G9: =SUMPRODUCT($C7:$C8,G7:G8)-G6 -> -70 | H9: =SUMPRODUCT($C7:$C8,H7:H8)-H6 -> 0 | I9: =SUMPRODUCT($C7:$C8,I7:I8)-I6 -> 0
A12: Итер. | B12: Базис | C12: Cб | D12: b | E12: x1 | F12: x2 | G12: x3 | H12: x4 | I12: x5 | J12: b / a
D13: cj → | E13: =E$6 -> 50 | F13: =F$6 -> 65 | G13: =G$6 -> 70 | H13: =H$6 -> 0 | I13: =I$6 -> 0
A14: 1 | B14: x3 | C14: =G$6 -> 70 | D14: =D7/$G$7 -> 150 | E14: =E7/$G$7 -> 0.5 | F14: =F7/$G$7 -> 0.66666667 | G14: =G7/$G$7 -> 1 | H14: =H7/$G$7 -> 0.33333333 | I14: =I7/$G$7 -> 0 | J14: =IF(F14>0,D14/F14,"-") -> 225
B15: x5 | C15: =I$6 -> 0 | D15: =D8-$G8*D14 -> 375 | E15: =E8-$G8*E14 -> 2.25 | F15: =F8-$G8*F14 -> 1 | G15: =G8-$G8*G14 -> 0 | H15: =H8-$G8*H14 -> -0.5 | I15: =I8-$G8*I14 -> 1 | J15: =IF(F15>0,D15/F15,"-") -> 375
B16: Δ | D16: =SUMPRODUCT($C14:$C15,D14:D15) -> 10500 | E16: =SUMPRODUCT($C14:$C15,E14:E15)-E13 -> -15 | F16: =SUMPRODUCT($C14:$C15,F14:F15)-F13 -> -18.333333 | G16: =SUMPRODUCT($C14:$C15,G14:G15)-G13 -> 0 | H16: =SUMPRODUCT($C14:$C15,H14:H15)-H13 -> 23.333333 | I16: =SUMPRODUCT($C14:$C15,I14:I15)-I13 -> 0
A19: Итер. | B19: Базис | C19: Cб | D19: b | E19: x1 | F19: x2 | G19: x3 | H19: x4 | I19: x5 | J19: b / a
D20: cj → | E20: =E$6 -> 50 | F20: =F$6 -> 65 | G20: =G$6 -> 70 | H20: =H$6 -> 0 | I20: =I$6 -> 0
A21: 2 | B21: x2 | C21: =F$6 -> 65 | D21: =D14/$F$14 -> 225 | E21: =E14/$F$14 -> 0.75 | F21: =F14/$F$14 -> 1 | G21: =G14/$F$14 -> 1.5 | H21: =H14/$F$14 -> 0.5 | I21: =I14/$F$14 -> 0 | J21: =IF(E21>0,D21/E21,"-") -> 300
B22: x5 | C22: =I$6 -> 0 | D22: =D15-$F15*D21 -> 150 | E22: =E15-$F15*E21 -> 1.5 | F22: =F15-$F15*F21 -> 0 | G22: =G15-$F15*G21 -> -1.5 | H22: =H15-$F15*H21 -> -1 | I22: =I15-$F15*I21 -> 1 | J22: =IF(E22>0,D22/E22,"-") -> 100
B23: Δ | D23: =SUMPRODUCT($C21:$C22,D21:D22) -> 14625 | E23: =SUMPRODUCT($C21:$C22,E21:E22)-E20 -> -1.25 | F23: =SUMPRODUCT($C21:$C22,F21:F22)-F20 -> 0 | G23: =SUMPRODUCT($C21:$C22,G21:G22)-G20 -> 27.5 | H23: =SUMPRODUCT($C21:$C22,H21:H22)-H20 -> 32.5 | I23: =SUMPRODUCT($C21:$C22,I21:I22)-I20 -> 0
A26: Итер. | B26: Базис | C26: Cб | D26: b | E26: x1 | F26: x2 | G26: x3 | H26: x4 | I26: x5 | J26: b / a
D27: cj → | E27: =E$6 -> 50 | F27: =F$6 -> 65 | G27: =G$6 -> 70 | H27: =H$6 -> 0 | I27: =I$6 -> 0
A28: 3 | B28: x2 | C28: =F$6 -> 65 | D28: =D21-$E21*D29 -> 150 | E28: =E21-$E21*E29 -> 0 | F28: =F21-$E21*F29 -> 1 | G28: =G21-$E21*G29 -> 2.25 | H28: =H21-$E21*H29 -> 1 | I28: =I21-$E21*I29 -> -0.5 | J28: -
B29: x1 | C29: =E$6 -> 50 | D29: =D22/$E$22 -> 100 | E29: =E22/$E$22 -> 1 | F29: =F22/$E$22 -> 0 | G29: =G22/$E$22 -> -1 | H29: =H22/$E$22 -> -0.66666667 | I29: =I22/$E$22 -> 0.66666667 | J29: -
B30: Δ | D30: =SUMPRODUCT($C28:$C29,D28:D29) -> 14750 | E30: =SUMPRODUCT($C28:$C29,E28:E29)-E27 -> 0 | F30: =SUMPRODUCT($C28:$C29,F28:F29)-F27 -> 0 | G30: =SUMPRODUCT($C28:$C29,G28:G29)-G27 -> 26.25 | H30: =SUMPRODUCT($C28:$C29,H28:H29)-H27 -> 31.666667 | I30: =SUMPRODUCT($C28:$C29,I28:I29)-I27 -> 0.83333333
B31: соответствует → | E31: y4 | F31: y5 | G31: y6 | H31: y1 | I31: y2
A33: Итог симплекс-метода
A34: Все Δj ≥ 0? | E34: =IF(MIN(E30:I30)>=-0.000001,"да - план оптимален","нет - нужна ещё итерация") -> да - план оптимален
A35: x1 (П1), тыс. р. | E35: =D29 -> 100
A36: x2 (П2), тыс. р. | E36: =D28 -> 150
A37: x3 (П3), тыс. р. | E37: 0
A38: Z max, ден. ед. | E38: =D30 -> 14750
A39: Проверка товарооборота | E39: =IF(D28+D29>=Условие!F8,"x1+x2+x3 = "&ROUND(D28+D29,2)&" ≥ 240 - выполнено","не выполнено") -> x1+x2+x3 = 250 ≥ 240 - выполнено
A40: x6 - превышение 240, тыс. р. | E40: =D28+D29-Условие!F8 -> 10
A41: y* (y1; y2; y3) | E41: ="("&ROUND(H30,3)&"; "&ROUND(I30,3)&"; 0)" -> (31.667; 0.833; 0)

Sheet Отчет о результатах 2
A1: Microsoft Excel 16.0 Отчет о результатах
A2: Лист: [ЛР2 В8 Деверилин 451003.xlsx]Двойственная задача
A3: Отчет создан: 11/10/2026 16:58:08
A4: Результат: Решение найдено. Все ограничения и условия оптимальности выполнены.
A5: Модуль поиска решения
B6: Модуль: Поиск решения лин. задач симплекс-методом
B7: Время решения: 0.016 секунд.
B8: Число итераций: 4 Число подзадач: 0
A9: Параметры поиска решения
B10: Максимальное время Без пределов, Число итераций Без пределов, Precision 0.000001, Использовать автоматическое масштабирование
B11: Максимальное число подзадач Без пределов, Максимальное число целочисленных решений Без пределов, Целочисленное отклонение 1%, Считать неотрицательными
A14: Ячейка целевой функции (Минимум)
B15: Ячейка | C15: Имя | D15: Исходное значение | E15: Окончательное значение
B16: $F$6 | C16: f = | D16: 14750 | E16: 14750
A19: Ячейки переменных
B20: Ячейка | C20: Имя | D20: Исходное значение | E20: Окончательное значение | F20: Целочисленное
B21: $B$5 | C21: Оценка, ден. ед. за единицу y1 (площадь) | D21: 31.666667 | E21: 31.666667 | F21: Продолжить
B22: $C$5 | C22: Оценка, ден. ед. за единицу y2 (время) | D22: 0.83333333 | E22: 0.83333333 | F22: Продолжить
B23: $D$5 | C23: Оценка, ден. ед. за единицу y3 (товарооб.) | D23: 0 | E23: 0 | F23: Продолжить
A26: Ограничения
B27: Ячейка | C27: Имя | D27: Значение ячейки | E27: Формула | F27: Состояние | G27: Допуск
B28: $E$9 | C28: П1 Левая часть | D28: 50 | E28: $E$9>=$G$9 | F28: Привязка | G28: 0
B29: $E$10 | C29: П2 Левая часть | D29: 65 | E29: $E$10>=$G$10 | F29: Привязка | G29: 0
B30: $E$11 | C30: П3 Левая часть | D30: 96.25 | E30: $E$11>=$G$11 | F30: Без привязки | G30: 26.25

Sheet Отчет об устойчивости 2
A1: Microsoft Excel 16.0 Отчет об устойчивости
A2: Лист: [ЛР2 В8 Деверилин 451003.xlsx]Двойственная задача
A3: Отчет создан: 11/10/2026 16:58:08
A6: Ячейки переменных
D7: Окончательное | E7: Приведенн. | F7: Целевая функция | G7: Допустимое | H7: Допустимое
B8: Ячейка | C8: Имя | D8: Значение | E8: Стоимость | F8: Коэффициент | G8: Увеличение | H8: Уменьшение
B9: $B$5 | C9: Оценка, ден. ед. за единицу y1 (площадь) | D9: 31.666667 | E9: 0 | F9: 450 | G9: 150 | H9: 30
B10: $C$5 | C10: Оценка, ден. ед. за единицу y2 (время) | D10: 0.83333333 | E10: 0 | F10: 600 | G10: 300 | H10: 60
B11: $D$5 | C11: Оценка, ден. ед. за единицу y3 (товарооб.) | D11: 0 | E11: 10 | F11: -240 | G11: 1e+30 | H11: 10
A13: Ограничения
D14: Окончательное | E14: Тень | F14: Ограничение | G14: Допустимое | H14: Допустимое
B15: Ячейка | C15: Имя | D15: Значение | E15: Цена | F15: Правая сторона | G15: Увеличение | H15: Уменьшение
B16: $E$9 | C16: П1 Левая часть | D16: 50 | E16: 100 | F16: 50 | G16: 26.25 | H16: 1.25
B17: $E$10 | C17: П2 Левая часть | D17: 65 | E17: 150 | F17: 65 | G17: 1.6666667 | H17: 11.666667
B18: $E$11 | C18: П3 Левая часть | D18: 96.25 | E18: 0 | F18: 70 | G18: 26.25 | H18: 1e+30

Sheet Отчет о пределах 2
A1: Microsoft Excel 16.0 Отчет о пределах
A2: Лист: [ЛР2 В8 Деверилин 451003.xlsx]Двойственная задача
A3: Отчет создан: 11/10/2026 16:58:08
C6: Целевая функция
B7: Ячейка | C7: Имя | D7: Значение
B8: $F$6 | C8: f = | D8: 14750
C11: Переменная | F11: Нижний | G11: Целевая функция | I11: Верхний | J11: Целевая функция
B12: Ячейка | C12: Имя | D12: Значение | F12: Предел | G12: Результат | I12: Предел | J12: Результат
B13: $B$5 | C13: Оценка, ден. ед. за единицу y1 (площадь) | D13: 31.666667 | F13: 31.666667 | G13: 14750 | I13: #Н/Д | J13: #Н/Д
B14: $C$5 | C14: Оценка, ден. ед. за единицу y2 (время) | D14: 0.83333333 | F14: 0.83333333 | G14: 14750 | I14: #Н/Д | J14: #Н/Д
B15: $D$5 | C15: Оценка, ден. ед. за единицу y3 (товарооб.) | D15: 0 | F15: 0 | G15: 14750 | I15: 0 | J15: 14750

Sheet Двойственная задача
A1: Двойственная задача: решение с помощью «Поиск решения»
A4: Переменная | B4: y1 (площадь) | C4: y2 (время) | D4: y3 (товарооб.)
A5: Оценка, ден. ед. за единицу | B5: 31.666667 | C5: 0.83333333 | D5: 0
A6: Коэффициенты f | B6: =Условие!F6 -> 450 | C6: =Условие!F7 -> 600 | D6: =-Условие!F8 -> -240 | E6: f = | F6: =SUMPRODUCT($B$5:$D$5,B6:D6) -> 14750 | H6: → min
A8: Ограничение (товар) | B8: y1 | C8: y2 | D8: y3 | E8: Левая часть | F8: Знак | G8: Правая часть | H8: Разница | I8: Вывод
A9: П1 | B9: =Условие!B6 -> 1.5 | C9: =Условие!B7 -> 3 | D9: =-Условие!B8 -> -1 | E9: =SUMPRODUCT($B$5:$D$5,B9:D9) -> 50 | F9: >= | G9: =Условие!B9 -> 50 | H9: =E9-G9 -> 0 | I9: =IF(ABS(H9)<0.000001,"равенство → товар выгоден (входит в план)","ресурсы дороже прибыли → товар невыгоден, −"&ROUND(H9,2)&" на 1 тыс. р.") -> равенство → товар выгоден (входит в план)
A10: П2 | B10: =Условие!C6 -> 2 | C10: =Условие!C7 -> 2 | D10: =-Условие!C8 -> -1 | E10: =SUMPRODUCT($B$5:$D$5,B10:D10) -> 65 | F10: >= | G10: =Условие!C9 -> 65 | H10: =E10-G10 -> 0 | I10: =IF(ABS(H10)<0.000001,"равенство → товар выгоден (входит в план)","ресурсы дороже прибыли → товар невыгоден, −"&ROUND(H10,2)&" на 1 тыс. р.") -> равенство → товар выгоден (входит в план)
A11: П3 | B11: =Условие!D6 -> 3 | C11: =Условие!D7 -> 1.5 | D11: =-Условие!D8 -> -1 | E11: =SUMPRODUCT($B$5:$D$5,B11:D11) -> 96.25 | F11: >= | G11: =Условие!D9 -> 70 | H11: =E11-G11 -> 26.25 | I11: =IF(ABS(H11)<0.000001,"равенство → товар выгоден (входит в план)","ресурсы дороже прибыли → товар невыгоден, −"&ROUND(H11,2)&" на 1 тыс. р.") -> ресурсы дороже прибыли → товар невыгоден, −26.25 на 1 тыс. р.
A13: Сравнение с прямой задачей (1-я теорема двойственности)
A14: Z max прямой задачи | B14: ='Прямая задача'!F6 -> 14750
A15: f min двойственной задачи | B15: =F6 -> 14750
A16: Совпадают? | B16: =IF(ABS(B14-B15)<0.001,"да: Z max = f min - решения верны","нет") -> да: Z max = f min - решения верны
A17: y1, y2 из симплекс-таблицы | B17: =ROUND('Симплекс-метод'!H30,3)&"; "&ROUND('Симплекс-метод'!I30,3)&" - те же, что в B5:C5" -> 31.667; 0.833 - те же, что в B5:C5
